{
 "type": "A",
 "title": "Textos y booleanos",
 "description": "Contenido de la lección «5. Textos y booleanos»",
 "printDescription": "Página para imprimir de la lección «5. Textos y booleanos».",
 "listado": [
  {
   "name": "mAcaracter.html",
   "title": "Caracter",
   "h1": "<dfn>Caracter</dfn>",
   "description": "Definición de cracter."
  },
  {
   "name": "mBtexto.html",
   "title": "Cadena de texto",
   "description": "Definición de cadena de texto."
  },
  {
   "name": "mCcodificacion.html",
   "title": "Codificación",
   "h1": "<dfn>Codificación</dfn>",
   "description": "Definición de codificación."
  },
  {
   "name": "mDboolean.html",
   "title": "Booleano",
   "h1": "<dfn>Booleano</dfn>",
   "description": "Definición de booleano."
  },
  {
   "name": "mEresumen.html",
   "title": "Resumen",
   "description": "Resumen de la lección «5. Textos y booleanos»."
    }
 ]
}